aori_sdk_py/__init__.py
aori_sdk_py/sdk.py
src/__init__.py
src/sdk.py
aori_sdk_py-0.6.dist-info/LICENSE
aori_sdk_py-0.6.dist-info/METADATA
aori_sdk_py-0.6.dist-info/WHEEL
aori_sdk_py-0.6.dist-info/top_level.txt
aori_sdk_py-0.6.dist-info/RECORD
